{"city":{"id":2643744,"name":"City of London","coord":{"lon":-0.08901,"lat":51.51334},"country":"GB","population":0,"sys":{"population":0}},"cod":"200","message":0.2058,"cnt":40,"list":[{"dt":1480010400,"main":{"temp":281.01,"temp_min":281.01,"temp_max":281.601,"pressure":1029.52,"sea_level":1037.25,"grnd_level":1029.52,"humidity":79,"temp_kf":-0.6},"weather":[{"id":800,"main":"Clear","description":"clear sky","icon":"02n"}],"clouds":{"all":8},"wind":{"speed":6.41,"deg":56.004},"rain":{},"sys":{"pod":"n"},"dt_txt":"2016-11-24 18:00:00"},{"dt":1480021200,"main":{"temp":280.45,"temp_min":280.45,"temp_max":280.849,"pressure":1029.64,"sea_level":1037.4,"grnd_level":1029.64,"humidity":80,"temp_kf":-0.4},"weather":[{"id":800,"main":"Clear","description":"clear sky","icon":"01n"}],"clouds":{"all":0},"wind":{"speed":5.93,"deg":54.5101},"rain":{},"sys":{"pod":"n"},"dt_txt":"2016-11-24 21:00:00"},{"dt":1480032000,"main":{"temp":279.97,"temp_min":279.97,"temp_max":280.168,"pressure":1030.03,"sea_level":1037.72,"grnd_level":1030.03,"humidity":80,"temp_kf":-0.2},"weather":[{"id":800,"main":"Clear","description":"clear sky","icon":"01n"}],"clouds":{"all":0},"wind":{"speed":5.94,"deg":54.0053},"rain":{},"sys":{"pod":"n"},"dt_txt":"2016-11-25 00:00:00"},{"dt":1480042800,"main":{"temp":279.767,"temp_min":279.767,"temp_max":279.767,"pressure":1029.06,"sea_level":1036.89,"grnd_level":1029.06,"humidity":79,"temp_kf":0},"weather":[{"id":800,"main":"Clear","description":"clear sky","icon":"01n"}],"clouds":{"all":0},"wind":{"speed":5.66,"deg":56.002},"rain":{},"sys":{"pod":"n"},"dt_txt":"2016-11-25 03:00:00"},{"dt":1480053600,"main":{"temp":279.546,"temp_min":279.546,"temp_max":279.546,"pressure":1029.24,"sea_level":1036.97,"grnd_level":1029.24,"humidity":77,"temp_kf":0},"weather":[{"id":800,"main":"Clear","description":"clear sky","icon":"01n"}],"clouds":{"all":0},"wind":{"speed":5.57,"deg":60.012},"rain":{},"sys":{"pod":"n"},"dt_txt":"2016-11-25 06:00:00"},{"dt":1480064400,"main":{"temp":279.889,"temp_min":279.889,"temp_max":279.889,"pressure":1029.45,"sea_level":1037.19,"grnd_level":1029.45,"humidity":78,"temp_kf":0},"weather":[{"id":800,"main":"Clear","description":"clear sky","icon":"01d"}],"clouds":{"all":0},"wind":{"speed":5.56,"deg":59.5018},"rain":{},"sys":{"pod":"d"},"dt_txt":"2016-11-25 09:00:00"},{"dt":1480075200,"main":{"temp":282.274,"temp_min":282.274,"temp_max":282.274,"pressure":1029.26,"sea_level":1037,"grnd_level":1029.26,"humidity":75,"temp_kf":0},"weather":[{"id":800,"main":"Clear","description":"clear sky","icon":"01d"}],"clouds":{"all":0},"wind":{"speed":6,"deg":63.0039},"rain":{},"sys":{"pod":"d"},"dt_txt":"2016-11-25 12:00:00"},{"dt":1480086000,"main":{"temp":281.503,"temp_min":281.503,"temp_max":281.503,"pressure":1028.56,"sea_level":1036.29,"grnd_level":1028.56,"humidity":72,"temp_kf":0},"weather":[{"id":800,"main":"Clear","description":"clear sky","icon":"01d"}],"clouds":{"all":0},"wind":{"speed":6.11,"deg":60.5001},"rain":{},"sys":{"pod":"d"},"dt_txt":"2016-11-25 15:00:00"},{"dt":1480096800,"main":{"temp":280.065,"temp_min":280.065,"temp_max":280.065,"pressure":1028.53,"sea_level":1036.25,"grnd_level":1028.53,"humidity":73,"temp_kf":0},"weather":[{"id":800,"main":"Clear","description":"clear sky","icon":"01n"}],"clouds":{"all":0},"wind":{"speed":5.8,"deg":57.0013},"rain":{},"sys":{"pod":"n"},"dt_txt":"2016-11-25 18:00:00"},{"dt":1480107600,"main":{"temp":279.555,"temp_min":279.555,"temp_max":279.555,"pressure":1028.11,"sea_level":1035.94,"grnd_level":1028.11,"humidity":85,"temp_kf":0},"weather":[{"id":800,"main":"Clear","description":"clear sky","icon":"01n"}],"clouds":{"all":0},"wind":{"speed":5.21,"deg":57.0081},"rain":{},"sys":{"pod":"n"},"dt_txt":"2016-11-25 21:00:00"},{"dt":1480118400,"main":{"temp":279.153,"temp_min":279.153,"temp_max":279.153,"pressure":1027.86,"sea_level":1035.56,"grnd_level":1027.86,"humidity":91,"temp_kf":0},"weather":[{"id":800,"main":"Clear","description":"clear sky","icon":"01n"}],"clouds":{"all":0},"wind":{"speed":4.66,"deg":53.5031},"rain":{},"sys":{"pod":"n"},"dt_txt":"2016-11-26 00:00:00"},{"dt":1480129200,"main":{"temp":278.564,"temp_min":278.564,"temp_max":278.564,"pressure":1027.1,"sea_level":1034.81,"grnd_level":1027.1,"humidity":93,"temp_kf":0},"weather":[{"id":800,"main":"Clear","description":"clear sky","icon":"01n"}],"clouds":{"all":0},"wind":{"speed":4.32,"deg":50.5025},"rain":{},"sys":{"pod":"n"},"dt_txt":"2016-11-26 03:00:00"},{"dt":1480140000,"main":{"temp":278.133,"temp_min":278.133,"temp_max":278.133,"pressure":1026.48,"sea_level":1034.33,"grnd_level":1026.48,"humidity":96,"temp_kf":0},"weather":[{"id":800,"main":"Clear","description":"clear sky","icon":"01n"}],"clouds":{"all":0},"wind":{"speed":4.17,"deg":47.5052},"rain":{},"sys":{"pod":"n"},"dt_txt":"2016-11-26 06:00:00"},{"dt":1480150800,"main":{"temp":278.788,"temp_min":278.788,"temp_max":278.788,"pressure":1026.77,"sea_level":1034.46,"grnd_level":1026.77,"humidity":95,"temp_kf":0},"weather":[{"id":800,"main":"Clear","description":"clear sky","icon":"01d"}],"clouds":{"all":0},"wind":{"speed":4.17,"deg":45.5028},"rain":{},"sys":{"pod":"d"},"dt_txt":"2016-11-26 09:00:00"},{"dt":1480161600,"main":{"temp":282.62,"temp_min":282.62,"temp_max":282.62,"pressure":1025.92,"sea_level":1033.67,"grnd_level":1025.92,"humidity":80,"temp_kf":0},"weather":[{"id":800,"main":"Clear","description":"clear sky","icon":"01d"}],"clouds":{"all":0},"wind":{"speed":4.57,"deg":52.0001},"rain":{},"sys":{"pod":"d"},"dt_txt":"2016-11-26 12:00:00"},{"dt":1480172400,"main":{"temp":282.337,"temp_min":282.337,"temp_max":282.337,"pressure":1025.26,"sea_level":1032.99,"grnd_level":1025.26,"humidity":77,"temp_kf":0},"weather":[{"id":802,"main":"Clouds","description":"scattered clouds","icon":"03d"}],"clouds":{"all":36},"wind":{"speed":4.66,"deg":53.5005},"rain":{},"sys":{"pod":"d"},"dt_txt":"2016-11-26 15:00:00"},{"dt":1480183200,"main":{"temp":281.049,"temp_min":281.049,"temp_max":281.049,"pressure":1025.65,"sea_level":1033.35,"grnd_level":1025.65,"humidity":83,"temp_kf":0},"weather":[{"id":500,"main":"Rain","description":"light rain","icon":"10n"}],"clouds":{"all":68},"wind":{"speed":4.21,"deg":49.5},"rain":{"3h":0.0375},"sys":{"pod":"n"},"dt_txt":"2016-11-26 18:00:00"},{"dt":1480194000,"main":{"temp":278.345,"temp_min":278.345,"temp_max":278.345,"pressure":1026.11,"sea_level":1033.83,"grnd_level":1026.11,"humidity":93,"temp_kf":0},"weather":[{"id":500,"main":"Rain","description":"light rain","icon":"10n"}],"clouds":{"all":20},"wind":{"speed":3.77,"deg":37.5039},"rain":{"3h":0.03},"sys":{"pod":"n"},"dt_txt":"2016-11-26 21:00:00"},{"dt":1480204800,"main":{"temp":276.472,"temp_min":276.472,"temp_max":276.472,"pressure":1026.17,"sea_level":1033.97,"grnd_level":1026.17,"humidity":100,"temp_kf":0},"weather":[{"id":801,"main":"Clouds","description":"few clouds","icon":"02n"}],"clouds":{"all":12},"wind":{"speed":3.06,"deg":24.0007},"rain":{},"sys":{"pod":"n"},"dt_txt":"2016-11-27 00:00:00"},{"dt":1480215600,"main":{"temp":277.496,"temp_min":277.496,"temp_max":277.496,"pressure":1026.02,"sea_level":1033.89,"grnd_level":1026.02,"humidity":100,"temp_kf":0},"weather":[{"id":500,"main":"Rain","description":"light rain","icon":"10n"}],"clouds":{"all":88},"wind":{"speed":2.86,"deg":11.0004},"rain":{"3h":0.04},"sys":{"pod":"n"},"dt_txt":"2016-11-27 03:00:00"},{"dt":1480226400,"main":{"temp":280.053,"temp_min":280.053,"temp_max":280.053,"pressure":1026.22,"sea_level":1033.95,"grnd_level":1026.22,"humidity":100,"temp_kf":0},"weather":[{"id":500,"main":"Rain","description":"light rain","icon":"10n"}],"clouds":{"all":92},"wind":{"speed":3.4,"deg":27.5078},"rain":{"3h":0.2},"sys":{"pod":"n"},"dt_txt":"2016-11-27 06:00:00"},{"dt":1480237200,"main":{"temp":281.113,"temp_min":281.113,"temp_max":281.113,"pressure":1027.53,"sea_level":1035.28,"grnd_level":1027.53,"humidity":96,"temp_kf":0},"weather":[{"id":500,"main":"Rain","description":"light rain","icon":"10d"}],"clouds":{"all":88},"wind":{"speed":4.3,"deg":35.0021},"rain":{"3h":0.12},"sys":{"pod":"d"},"dt_txt":"2016-11-27 09:00:00"},{"dt":1480248000,"main":{"temp":282.104,"temp_min":282.104,"temp_max":282.104,"pressure":1028.24,"sea_level":1035.86,"grnd_level":1028.24,"humidity":86,"temp_kf":0},"weather":[{"id":500,"main":"Rain","description":"light rain","icon":"10d"}],"clouds":{"all":80},"wind":{"speed":4.94,"deg":46.0034},"rain":{"3h":0.01},"sys":{"pod":"d"},"dt_txt":"2016-11-27 12:00:00"},{"dt":1480258800,"main":{"temp":282.014,"temp_min":282.014,"temp_max":282.014,"pressure":1028.7,"sea_level":1036.32,"grnd_level":1028.7,"humidity":84,"temp_kf":0},"weather":[{"id":500,"main":"Rain","description":"light rain","icon":"10d"}],"clouds":{"all":92},"wind":{"speed":4.74,"deg":50.5011},"rain":{"3h":0.09},"sys":{"pod":"d"},"dt_txt":"2016-11-27 15:00:00"},{"dt":1480269600,"main":{"temp":281.423,"temp_min":281.423,"temp_max":281.423,"pressure":1029.67,"sea_level":1037.45,"grnd_level":1029.67,"humidity":81,"temp_kf":0},"weather":[{"id":500,"main":"Rain","description":"light rain","icon":"10n"}],"clouds":{"all":92},"wind":{"speed":4.6,"deg":45.5001},"rain":{"3h":0.05},"sys":{"pod":"n"},"dt_txt":"2016-11-27 18:00:00"},{"dt":1480280400,"main":{"temp":281.011,"temp_min":281.011,"temp_max":281.011,"pressure":1030.59,"sea_level":1038.31,"grnd_level":1030.59,"humidity":82,"temp_kf":0},"weather":[{"id":500,"main":"Rain","description":"light rain","icon":"10n"}],"clouds":{"all":88},"wind":{"speed":4.74,"deg":45.5024},"rain":{"3h":0.04},"sys":{"pod":"n"},"dt_txt":"2016-11-27 21:00:00"},{"dt":1480291200,"main":{"temp":280.361,"temp_min":280.361,"temp_max":280.361,"pressure":1030.92,"sea_level":1038.62,"grnd_level":1030.92,"humidity":82,"temp_kf":0},"weather":[{"id":500,"main":"Rain","description":"light rain","icon":"10n"}],"clouds":{"all":80},"wind":{"speed":4.31,"deg":44.003},"rain":{"3h":0.03},"sys":{"pod":"n"},"dt_txt":"2016-11-28 00:00:00"},{"dt":1480302000,"main":{"temp":280.833,"temp_min":280.833,"temp_max":280.833,"pressure":1030.84,"sea_level":1038.67,"grnd_level":1030.84,"humidity":83,"temp_kf":0},"weather":[{"id":500,"main":"Rain","description":"light rain","icon":"10n"}],"clouds":{"all":92},"wind":{"speed":3.57,"deg":59.5016},"rain":{"3h":0.06},"sys":{"pod":"n"},"dt_txt":"2016-11-28 03:00:00"},{"dt":1480312800,"main":{"temp":279.22,"temp_min":279.22,"temp_max":279.22,"pressure":1031.48,"sea_level":1039.28,"grnd_level":1031.48,"humidity":81,"temp_kf":0},"weather":[{"id":800,"main":"Clear","description":"clear sky","icon":"01n"}],"clouds":{"all":0},"wind":{"speed":3.91,"deg":82.0069},"rain":{},"sys":{"pod":"n"},"dt_txt":"2016-11-28 06:00:00"},{"dt":1480323600,"main":{"temp":278.87,"temp_min":278.87,"temp_max":278.87,"pressure":1033.09,"sea_level":1041.04,"grnd_level":1033.09,"humidity":81,"temp_kf":0},"weather":[{"id":800,"main":"Clear","description":"clear sky","icon":"01d"}],"clouds":{"all":0},"wind":{"speed":4.32,"deg":99.5006},"rain":{},"sys":{"pod":"d"},"dt_txt":"2016-11-28 09:00:00"},{"dt":1480334400,"main":{"temp":280.951,"temp_min":280.951,"temp_max":280.951,"pressure":1033.71,"sea_level":1041.5,"grnd_level":1033.71,"humidity":75,"temp_kf":0},"weather":[{"id":800,"main":"Clear","description":"clear sky","icon":"01d"}],"clouds":{"all":0},"wind":{"speed":5.22,"deg":98.502},"rain":{},"sys":{"pod":"d"},"dt_txt":"2016-11-28 12:00:00"},{"dt":1480345200,"main":{"temp":279.417,"temp_min":279.417,"temp_max":279.417,"pressure":1033.73,"sea_level":1041.53,"grnd_level":1033.73,"humidity":73,"temp_kf":0},"weather":[{"id":800,"main":"Clear","description":"clear sky","icon":"01d"}],"clouds":{"all":0},"wind":{"speed":5.21,"deg":95.0009},"rain":{},"sys":{"pod":"d"},"dt_txt":"2016-11-28 15:00:00"},{"dt":1480356000,"main":{"temp":277.374,"temp_min":277.374,"temp_max":277.374,"pressure":1034.47,"sea_level":1042.4,"grnd_level":1034.47,"humidity":72,"temp_kf":0},"weather":[{"id":800,"main":"Clear","description":"clear sky","icon":"01n"}],"clouds":{"all":0},"wind":{"speed":4.87,"deg":94.5017},"rain":{},"sys":{"pod":"n"},"dt_txt":"2016-11-28 18:00:00"},{"dt":1480366800,"main":{"temp":276.9,"temp_min":276.9,"temp_max":276.9,"pressure":1035.16,"sea_level":1043.15,"grnd_level":1035.16,"humidity":75,"temp_kf":0},"weather":[{"id":800,"main":"Clear","description":"clear sky","icon":"01n"}],"clouds":{"all":0},"wind":{"speed":4.36,"deg":105.5},"rain":{},"sys":{"pod":"n"},"dt_txt":"2016-11-28 21:00:00"},{"dt":1480377600,"main":{"temp":275.764,"temp_min":275.764,"temp_max":275.764,"pressure":1035.45,"sea_level":1043.4,"grnd_level":1035.45,"humidity":81,"temp_kf":0},"weather":[{"id":800,"main":"Clear","description":"clear sky","icon":"01n"}],"clouds":{"all":0},"wind":{"speed":3.46,"deg":115.001},"rain":{},"sys":{"pod":"n"},"dt_txt":"2016-11-29 00:00:00"},{"dt":1480388400,"main":{"temp":274.051,"temp_min":274.051,"temp_max":274.051,"pressure":1035.14,"sea_level":1043.19,"grnd_level":1035.14,"humidity":91,"temp_kf":0},"weather":[{"id":800,"main":"Clear","description":"clear sky","icon":"01n"}],"clouds":{"all":0},"wind":{"speed":2.76,"deg":113.007},"rain":{},"sys":{"pod":"n"},"dt_txt":"2016-11-29 03:00:00"},{"dt":1480399200,"main":{"temp":271.816,"temp_min":271.816,"temp_max":271.816,"pressure":1034.98,"sea_level":1043.06,"grnd_level":1034.98,"humidity":100,"temp_kf":0},"weather":[{"id":800,"main":"Clear","description":"clear sky","icon":"01n"}],"clouds":{"all":0},"wind":{"speed":1.81,"deg":103.001},"rain":{},"sys":{"pod":"n"},"dt_txt":"2016-11-29 06:00:00"},{"dt":1480410000,"main":{"temp":271.729,"temp_min":271.729,"temp_max":271.729,"pressure":1035.66,"sea_level":1043.68,"grnd_level":1035.66,"humidity":96,"temp_kf":0},"weather":[{"id":800,"main":"Clear","description":"clear sky","icon":"01d"}],"clouds":{"all":0},"wind":{"speed":1.31,"deg":103.005},"rain":{},"sys":{"pod":"d"},"dt_txt":"2016-11-29 09:00:00"},{"dt":1480420800,"main":{"temp":277.546,"temp_min":277.546,"temp_max":277.546,"pressure":1035.23,"sea_level":1043.14,"grnd_level":1035.23,"humidity":81,"temp_kf":0},"weather":[{"id":800,"main":"Clear","description":"clear sky","icon":"01d"}],"clouds":{"all":0},"wind":{"speed":1.75,"deg":142.002},"rain":{},"sys":{"pod":"d"},"dt_txt":"2016-11-29 12:00:00"},{"dt":1480431600,"main":{"temp":277.042,"temp_min":277.042,"temp_max":277.042,"pressure":1034.44,"sea_level":1042.41,"grnd_level":1034.44,"humidity":78,"temp_kf":0},"weather":[{"id":800,"main":"Clear","description":"clear sky","icon":"01d"}],"clouds":{"all":0},"wind":{"speed":1.25,"deg":18.0046},"rain":{},"sys":{"pod":"d"},"dt_txt":"2016-11-29 15:00:00"}]}
